{"guide_axios.md":"CUBtBbrl","guide_browsers.md":"BnYE08MT","guide_components.md":"BnQZRZWr","guide_environment.md":"KptfyQyH","guide_introduction.md":"BKYX8Ae9","guide_layouts.md":"BmMjRrPe","guide_library.md":"DP18g4qt","guide_mocks.md":"B1H9T9sW","guide_routers.md":"DrmKH46Y","guide_tests.md":"DZxpQQDG","guide_themes.md":"BG_NOa5U","guide_typescripts.md":"BsWvkk7T","index.md":"BycpgiVl","library_edit_cell.md":"BJaC8Pws","library_editcell_autocomplete.md":"D4ovPG6h","library_editcell_datepicker.md":"DyCJqT1k","library_editcell_input.md":"CzvwTw5j","library_editcell_select.md":"BIfc3fXJ","library_editcell_selecticon.md":"BfGRCSdI","library_editcell_textarea.md":"DJfHjy9d","library_editcell_treeselect.md":"BQBbjVGc","library_editcell_useinstable.md":"Dse0i1wl","library_ellipsis.md":"CsS11aye","library_ellipsis_base.md":"Den8kvHG","library_ellipsis_title.md":"iTIVjvmq","library_ellipsis_trigger.md":"52laQwbY","library_form.md":"BWVsKlWE","library_form_base.md":"Bhv9RO6G","library_form_check.md":"DjGkOWrB","library_form_componentslot.md":"D_pp2aXC","library_form_group.md":"DP7byokM","library_form_groupslot.md":"BHpxq2nd","library_icon.md":"C0rMArSU","library_icon_base.md":"Cy-pdMXX","library_icon_iconfont.md":"D4dAF1Hg","library_icon_select.md":"BQcCvcWR","library_icon_twotonecolor.md":"CF3J8OOW","library_iconselect_base.md":"DJA4zedT","library_iconselect_custom.md":"B0OmhBtm","library_iconselect_iconfont.md":"BBLDuykW","library_overview.md":"Vse_cg8G","library_quick.md":"BaQokr0N","library_table.md":"D_-S-Qz-","library_table_base.md":"oURwz6_q","library_table_checkbox.md":"BlRb_jaF","library_table_checkboxtree.md":"BBcnwo2r","library_table_customslots.md":"DbMq812N","library_table_diffsize.md":"l2sDQ4kU","library_table_edittable.md":"eGjLDi9T","library_table_ellipsis.md":"DvjwXtbW","library_table_events.md":"DgdRlNEi","library_table_expanded.md":"a94MLYzx","library_table_fixedpagetable.md":"BniBwvmd","library_table_fixedtable.md":"D1_X27OT","library_table_footer.md":"DHxH2jh0","library_table_loaddata.md":"CKn3eSJ_","library_table_merge.md":"BEur4-Ai","library_table_multiple.md":"CyIH5wkX","library_table_sorter.md":"B-O8Ib9z","library_table_sources.md":"Bs__RHCi","library_table_striped.md":"C4xNnsF8","library_tree.md":"DsM-Tovm","library_tree_accordion.md":"CLiCjh4V","library_tree_base.md":"DurGWy95","library_tree_checkedlevel.md":"D1RZD8hz","library_tree_customfield.md":"HWMitsSQ","library_tree_customslots.md":"CqdH_Zev","library_tree_disabled.md":"D_LyyvDw","library_tree_draggable.md":"DOaYLaT3","library_tree_loaddata.md":"BhFYeUs1","library_tree_mode.md":"Cl6CUSwD","library_tree_search.md":"ComdO2oG","mock_auth_login.md":"DOri6S2Y","mock_auth_loginuserinfo.md":"DrmKjJav","mock_auth_loginusermenu.md":"DAmPY-bC","mock_base_getoptionbyid.md":"CIMF46Lk","mock_base_gettreebyid.md":"zP6yFo40","mock_organize_getorganizeinfolist.md":"CCWAlCSN","mock_organize_getorganizeinfotree.md":"Ws5M-G4S","mock_resource_getresourcebuttonbyrole.md":"DFW3zhZ2","mock_resource_getresourcelistinfo.md":"ChFyBXdC","mock_resource_getresourcemenubyrole.md":"CG-H5wf3","mock_resource_getresourcetreeinfo.md":"DqRSGFbs","mock_role_getroleinfobypages.md":"C2ndE8eb","mock_role_getroleinfolist.md":"45_okdX8","mock_user_getuserinfolist.md":"C3CIvUNk","redirect.md":"rDAVXcq8","repository.md":"Dij49wyp","standard_develop_guide.md":"DomFlGzJ","standard_develop_vue3_1.md":"Mfuq4zvM","standard_develop_vue3_2.md":"C9h4_T_B","standard_git_branch.md":"ChALb6rD","standard_git_check.md":"CIM11S8M","standard_git_commit.md":"DEvXRlvZ","standard_git_helper.md":"B9Zab82r","standard_git_version.md":"BAODXVdl","standard_vscode_config.md":"DkIhu6cU","standard_vscode_plugin.md":"CNrXgLKS","standard_vscode_script.md":"Dofprk8m"}
